COPYING
COPYING.LESSER
MANIFEST.in
NEWS.rst
README.rst
setup.cfg
setup.py
pyjulius/__init__.py
pyjulius/core.py
pyjulius/exceptions.py
pyjulius/infos.py
pyjulius/models.py
pyjulius.egg-info/PKG-INFO
pyjulius.egg-info/SOURCES.txt
pyjulius.egg-info/dependency_links.txt
pyjulius.egg-info/top_level.txt