Metadata-Version: 1.0
Name: pyjulius
Version: 0.3
Summary: Simple interface to connect to a julius module server
Home-page: https://github.com/Diaoul/pyjulius
Author: Antoine Bertin
Author-email: diaoulael@gmail.com
License: LGPLv3
Keywords: julius speech recognition
Platform: UNKNOWN
Classifier: Development Status :: 4 - Beta
Classifier: License :: OSI Approved :: GNU Library or Lesser General Public License (LGPL)
Classifier: Intended Audience :: Developers
Classifier: Operating System :: OS Independent
Classifier: Programming Language :: Python :: 2.6
Classifier: Programming Language :: Python :: 2.7
Classifier: Topic :: Software Development :: Libraries :: Python Modules
